pushy/__init__.py
pushy/__main__.py
pushy/const.py
pushy/feed.py
pushy/main.py
pushy/notification.py
pushy/session.py
pushy/utils.py
pushy_api-0.2.1.dist-info/LICENSE.md
pushy_api-0.2.1.dist-info/METADATA
pushy_api-0.2.1.dist-info/WHEEL
pushy_api-0.2.1.dist-info/entry_points.txt
pushy_api-0.2.1.dist-info/top_level.txt
pushy_api-0.2.1.dist-info/RECORD
