Metadata-Version: 2.2
Name: pushy-api
Version: 0.2.1
Summary: An async Python client for Pushy HTTP API
Author-email: Vadim Averin <vadim@avevad.com>, Anton Egorov <ai_egorov@mail.ru>
License: MIT
Classifier: Programming Language :: Python :: 3
Classifier: License :: OSI Approved :: MIT License
Classifier: Operating System :: OS Independent
License-File: LICENSE.md
Requires-Dist: aiohttp
